setup.cfg
setup.py
protokoll/__init__.py
protokoll/__main__.py
protokoll/__version__.py
protokoll/db.py
protokoll/exception.py
protokoll.egg-info/PKG-INFO
protokoll.egg-info/SOURCES.txt
protokoll.egg-info/dependency_links.txt
protokoll.egg-info/entry_points.txt
protokoll.egg-info/requires.txt
protokoll.egg-info/top_level.txt