Metadata-Version: 1.1
Name: protokoll
Version: 0.2.1
Summary: Track time spent on tasks per project via the CLI
Home-page: https://github.com/metalseargolid/protokoll
Author: Alexander Alber
Author-email: metalseargolid@gmail.com
License: GPLv3
Download-URL: https://github.com/metalseargolid/protokoll/tarball/v0.2.1
Keywords: protokoll,time,log,track,timelog,timetrack,project,task
Platform: UNKNOWN
